happy_core/__init__.py
happy_core/collections.py
happy_core/enum_registry.py
happy_core/enums_toolkits.py
happy_core/exceptions.py
happy_core/re.py
happy_core/time.py
happy_core/toolkits.py
happy_core/types.py
happy_core-0.1.0.dist-info/LICENSE.md
happy_core-0.1.0.dist-info/LICENSE.txt
happy_core-0.1.0.dist-info/METADATA
happy_core-0.1.0.dist-info/WHEEL
happy_core-0.1.0.dist-info/RECORD
