Metadata-Version: 2.1
Name: happy_core
Version: 0.1.0
Summary: A boilerplate utility package
License: MIT
Author: alaamer12
Author-email: ahmedmuhmmed239@gmail.com
Requires-Python: >=3.11,<4.0
Classifier: License :: OSI Approved :: MIT License
Classifier: Programming Language :: Python :: 3
Classifier: Programming Language :: Python :: 3.11
Classifier: Programming Language :: Python :: 3.12
Classifier: Programming Language :: Python :: 3.13
Provides-Extra: jorunal
Provides-Extra: ulid
Requires-Dist: aiofiles (>=22.1.0,<23.0.0)
Requires-Dist: loguru (>=0.7.0,<0.8.0)
Requires-Dist: moviepy (>=1.0.3,<2.0.0)
Requires-Dist: pillow (>=9.4.0,<10.0.0)
Requires-Dist: psutil (>=6.1.0,<7.0.0)
Requires-Dist: pydub (>=0.25.1,<0.26.0)
Requires-Dist: pyjwt (>=2.6.0,<3.0.0)
Requires-Dist: pytz (>=2022.7.1,<2023.0.0)
Requires-Dist: uuid-utils (>=0.9.0,<0.10.0) ; extra == "ulid"
